safe_evaluation/__init__.py
safe_evaluation/expressions.py
tests/__init__.py
tests/test_allowed_funcs.py
tests/test_function_factory.py
tests/test_get_stack.py
tests/test_polish_notation.py
tests/test_valid_parentheses.py
safe_evaluation-0.1.4.dist-info/METADATA
safe_evaluation-0.1.4.dist-info/WHEEL
safe_evaluation-0.1.4.dist-info/top_level.txt
safe_evaluation-0.1.4.dist-info/RECORD
