Metadata-Version: 2.1
Name: safe-evaluation
Version: 0.1.4
Summary: package solves expressions
Home-page: https://github.com/lev4ek0/safe_eval
Author: Lev Belous
Author-email: leva22.08.01@inbox.ru
Requires-Python: >=3.9
Requires-Dist: pandas
Requires-Dist: numpy
